fast_litellm-0.1.6.dist-info/METADATA
fast_litellm-0.1.6.dist-info/WHEEL
fast_litellm-0.1.6.dist-info/licenses/LICENSE
fast_litellm/__init__.py
fast_litellm/__init__.pyi
fast_litellm/_rust.cpython-311-darwin.so
fast_litellm/diagnostics.py
fast_litellm/enhanced_monkeypatch.py
fast_litellm/feature_flags.json
fast_litellm/feature_flags.py
fast_litellm/performance_monitor.py
fast_litellm/py.typed
fast_litellm-0.1.6.dist-info/RECORD
