Metadata-Version: 2.4
Name: fast-litellm
Version: 0.1.6
Classifier: Development Status :: 4 - Beta
Classifier: Intended Audience :: Developers
Classifier: License :: OSI Approved :: MIT License
Classifier: Operating System :: OS Independent
Classifier: Programming Language :: Python :: 3
Classifier: Programming Language :: Python :: 3.8
Classifier: Programming Language :: Python :: 3.9
Classifier: Programming Language :: Python :: 3.10
Classifier: Programming Language :: Python :: 3.11
Classifier: Programming Language :: Python :: 3.12
Classifier: Programming Language :: Python :: 3.13
Classifier: Programming Language :: Rust
Classifier: Topic :: Scientific/Engineering :: Artificial Intelligence
Classifier: Topic :: Software Development :: Libraries :: Python Modules
Classifier: Topic :: System :: Networking
Classifier: Typing :: Typed
Requires-Dist: pydantic>=1.10.0
Requires-Dist: tiktoken>=0.5.0
Requires-Dist: aiohttp>=3.8.0
Requires-Dist: httpx>=0.24.0
Requires-Dist: pytest>=7.0.0 ; extra == 'dev'
Requires-Dist: pytest-asyncio>=0.21.0 ; extra == 'dev'
Requires-Dist: pytest-benchmark>=4.0.0 ; extra == 'dev'
Requires-Dist: pytest-cov>=4.0.0 ; extra == 'dev'
Requires-Dist: pytest-xdist>=3.0.0 ; extra == 'dev'
Requires-Dist: black>=23.0.0 ; extra == 'dev'
Requires-Dist: isort>=5.12.0 ; extra == 'dev'
Requires-Dist: flake8>=6.0.0 ; extra == 'dev'
Requires-Dist: mypy>=1.0.0 ; extra == 'dev'
Requires-Dist: ruff>=0.1.0 ; extra == 'dev'
Requires-Dist: sphinx>=5.0.0 ; extra == 'dev'
Requires-Dist: sphinx-rtd-theme>=1.2.0 ; extra == 'dev'
Requires-Dist: myst-parser>=0.18.0 ; extra == 'dev'
Requires-Dist: maturin>=1.0,<2.0 ; extra == 'dev'
Requires-Dist: pytest>=7.0.0 ; extra == 'test'
Requires-Dist: pytest-asyncio>=0.21.0 ; extra == 'test'
Requires-Dist: pytest-benchmark>=4.0.0 ; extra == 'test'
Requires-Dist: pytest-cov>=4.0.0 ; extra == 'test'
Requires-Dist: sphinx>=5.0.0 ; extra == 'docs'
Requires-Dist: sphinx-rtd-theme>=1.2.0 ; extra == 'docs'
Requires-Dist: myst-parser>=0.18.0 ; extra == 'docs'
Provides-Extra: dev
Provides-Extra: test
Provides-Extra: docs
License-File: LICENSE
Summary: High-performance Rust acceleration for LiteLLM
Keywords: llm,ai,performance,rust,acceleration,litellm,openai,anthropic,tokens,routing
Author: Fast LiteLLM Contributors
Maintainer: Fast LiteLLM Contributors
Requires-Python: >=3.8.1
Project-URL: Homepage, https://github.com/neul-labs/fast-litellm
Project-URL: Documentation, https://github.com/neul-labs/fast-litellm/tree/main/docs
Project-URL: Repository, https://github.com/neul-labs/fast-litellm.git
Project-URL: Bug Tracker, https://github.com/neul-labs/fast-litellm/issues
Project-URL: Changelog, https://github.com/neul-labs/fast-litellm/blob/main/CHANGELOG.md
